README.txt
setup.py
collective/__init__.py
collective.collage.imagetags.egg-info/PKG-INFO
collective.collage.imagetags.egg-info/SOURCES.txt
collective.collage.imagetags.egg-info/dependency_links.txt
collective.collage.imagetags.egg-info/entry_points.txt
collective.collage.imagetags.egg-info/namespace_packages.txt
collective.collage.imagetags.egg-info/not-zip-safe
collective.collage.imagetags.egg-info/requires.txt
collective.collage.imagetags.egg-info/top_level.txt
collective/collage/__init__.py
collective/collage/imagetags/__init__.py
collective/collage/imagetags/configure.zcml
collective/collage/imagetags/version.txt
collective/collage/imagetags/vocabulary.py
collective/collage/imagetags/browser/__init__.py
collective/collage/imagetags/browser/configure.zcml
collective/collage/imagetags/browser/interfaces.py
collective/collage/imagetags/browser/viewlets.py
collective/collage/imagetags/browser/views.py
collective/collage/imagetags/browser/templates/imagetags-settings-form.pt
collective/collage/imagetags/browser/templates/imagetags-settings.pt
collective/collage/imagetags/browser/templates/imagetags.pt
collective/collage/imagetags/docs/browser.txt
collective/collage/imagetags/locales/collective.collage.imagetags.pot
collective/collage/imagetags/locales/en/LC_MESSAGES/collective.collage.imagetags.mo
collective/collage/imagetags/locales/en/LC_MESSAGES/collective.collage.imagetags.po
collective/collage/imagetags/locales/es/LC_MESSAGES/collective.collage.imagetags.mo
collective/collage/imagetags/locales/es/LC_MESSAGES/collective.collage.imagetags.po
collective/collage/imagetags/profiles/default/metadata.xml
collective/collage/imagetags/tests/__init__.py
collective/collage/imagetags/tests/base.py
collective/collage/imagetags/tests/test_doctest.py
collective/collage/imagetags/tests/image_hack/__init__.py
collective/collage/imagetags/tests/image_hack/configure.zcml
collective/collage/imagetags/tests/image_hack/image_layout.pt
collective/collage/imagetags/tests/image_hack/image_layout.py
collective/collage/imagetags/tests/samples/test_image.png
docs/AUTHORS.txt
docs/HISTORY.txt
docs/INSTALL.txt
docs/LICENSE.GPL
docs/LICENSE.txt