Metadata-Version: 1.0
Name: collective.collage.imagetags
Version: 1.0.1
Summary: Collage view to display tagged images (collective.imagetags)
Home-page: http://svn.plone.org/svn/collective/collective.collage.imagetags
Author: Marcos F. Romero
Author-email: marcos.romero {at} inter-cultura {dot} com
License: GPL
Platform: UNKNOWN
Classifier: Framework :: Plone
Classifier: Programming Language :: Python
